rs_trader/__init__.py
rs_trader/main.py
rs_trader/interfaces/__init__.py
rs_trader/interfaces/database.py
rs_trader/storage/__init__.py
rs_trader/storage/json.py
rs_trader/structs/__init__.py
rs_trader/structs/structs.py
rs_trader-0.2.0.dist-info/LICENSE
rs_trader-0.2.0.dist-info/METADATA
rs_trader-0.2.0.dist-info/WHEEL
rs_trader-0.2.0.dist-info/top_level.txt
rs_trader-0.2.0.dist-info/RECORD
