Metadata-Version: 2.1
Name: rs-trader
Version: 0.2.0
Summary: Add your description here
Author: extreme4all
Project-URL: Homepage, https://github.com/extreme4all/rs_trader
Project-URL: Bug Tracker, https://github.com/extreme4all/rs_trader/issues
Requires-Python: >=3.9
License-File: LICENSE
Requires-Dist: pydantic>=2.9.2
